adminapi-1.4.3.0.1.1.dist-info/DESCRIPTION.rst
adminapi-1.4.3.0.1.1.dist-info/METADATA
adminapi-1.4.3.0.1.1.dist-info/RECORD
adminapi-1.4.3.0.1.1.dist-info/WHEEL
adminapi-1.4.3.0.1.1.dist-info/dependency_links.txt
adminapi-1.4.3.0.1.1.dist-info/metadata.json
adminapi-1.4.3.0.1.1.dist-info/top_level.txt
cloud_admin/__init__.py
cloud_admin/systemconnection.py
cloud_admin/access/__init__.py
cloud_admin/access/accessconnection.py
cloud_admin/access/account.py
cloud_admin/access/autocreds.py
cloud_admin/access/group.py
cloud_admin/access/user.py
cloud_admin/backends/__init__.py
cloud_admin/backends/block_storage/__init__.py
cloud_admin/backends/block_storage/threepar.py
cloud_admin/backends/network/__init__.py
cloud_admin/backends/network/eucanetxml.py
cloud_admin/backends/network/midget.py
cloud_admin/backends/object_storage/__init__.py
cloud_admin/cloudview/__init__.py
cloud_admin/cloudview/chefbuilder.py
cloud_admin/cloudview/eucalyptusblock.py
cloud_admin/cloudview/midokurabuilder.py
cloud_admin/cloudview/remote_calyptos.py
cloud_admin/hosts/__init__.py
cloud_admin/hosts/eucahost.py
cloud_admin/hosts/eucalyptusconf.py
cloud_admin/hosts/helpers/__init__.py
cloud_admin/hosts/helpers/cc_helpers.py
cloud_admin/hosts/helpers/clc_helpers.py
cloud_admin/hosts/helpers/dns_helpers.py
cloud_admin/hosts/helpers/helpernamespace.py
cloud_admin/hosts/helpers/midonethelpers.py
cloud_admin/hosts/helpers/nc_helpers.py
cloud_admin/hosts/helpers/osg_helpers.py
cloud_admin/hosts/helpers/sc_helpers.py
cloud_admin/services/__init__.py
cloud_admin/services/cloud_controller_service.py
cloud_admin/services/cluster.py
cloud_admin/services/cluster_controller_service.py
cloud_admin/services/dns_service.py
cloud_admin/services/eucaproperty.py
cloud_admin/services/node_service.py
cloud_admin/services/osg_service.py
cloud_admin/services/propertiesconnection.py
cloud_admin/services/service_certificate.py
cloud_admin/services/serviceconnection.py
cloud_admin/services/services.py
cloud_admin/services/storage_controller_service.py
cloud_admin/services/ufs.py
cloud_admin/services/walrus_service.py
cloud_utils/__init__.py
cloud_utils/file_utils/__init__.py
cloud_utils/file_utils/diagram_builders.py
cloud_utils/file_utils/eucarc.py
