Metadata-Version: 2.0
Name: adminapi
Version: 1.4.3.0.1.1
Summary: Eucalyptus Cloud Services and General System Administrative Utilities
Home-page: https://github.com/eucalyptus/adminapi
Author: UNKNOWN
Author-email: UNKNOWN
License: BSD (Simplified)
Platform: Posix; MacOS X;
Classifier: Development Status :: 3 - Alpha
Classifier: Intended Audience :: System Administrators
Classifier: Operating System :: OS Independent
Classifier: Topic :: System :: Systems Administration
Requires-Dist: argparse
Requires-Dist: boto (>=2.5.2)
Requires-Dist: dnspython
Requires-Dist: isodate
Requires-Dist: kazoo
Requires-Dist: midonetclient
Requires-Dist: paramiko (>=2.0.2)
Requires-Dist: prettytable
Requires-Dist: python-dateutil
Requires-Dist: pywinrm
Requires-Dist: requests (>=1)
